laserchicken/__init__.py
laserchicken/_version.py
laserchicken/_version.txt
laserchicken/build_volume.py
laserchicken/compute_neighbors.py
laserchicken/filter.py
laserchicken/kd_tree.py
laserchicken/keys.py
laserchicken/normalize.py
laserchicken/test_.py
laserchicken/test_build_volume.py
laserchicken/test_compute_neighbors.py
laserchicken/test_filter.py
laserchicken/test_integration_tests.py
laserchicken/test_kd_tree.py
laserchicken/test_normalize.py
laserchicken/test_tools.py
laserchicken/test_utils.py
laserchicken/test_version.py
laserchicken/test_volume_specification.py
laserchicken/utils.py
laserchicken/volume_specification.py
laserchicken/feature_extractor/__init__.py
laserchicken/feature_extractor/band_ratio_feature_extractor.py
laserchicken/feature_extractor/base_feature_extractor.py
laserchicken/feature_extractor/density_absolute_mean_feature_extractor.py
laserchicken/feature_extractor/density_feature_extractor.py
laserchicken/feature_extractor/echo_ratio_feature_extractor.py
laserchicken/feature_extractor/eigenvals_feature_extractor.py
laserchicken/feature_extractor/entropy_feature_extractor.py
laserchicken/feature_extractor/feature_extraction.py
laserchicken/feature_extractor/feature_map.py
laserchicken/feature_extractor/kurtosis_feature_extractor.py
laserchicken/feature_extractor/mean_std_coeff_feature_extractor.py
laserchicken/feature_extractor/median_feature_extractor.py
laserchicken/feature_extractor/percentile_feature_extractor.py
laserchicken/feature_extractor/pulse_penetration_feature_extractor.py
laserchicken/feature_extractor/range_feature_extractor.py
laserchicken/feature_extractor/sigma_z_feature_extractor.py
laserchicken/feature_extractor/skew_feature_extractor.py
laserchicken/feature_extractor/test_all_features.py
laserchicken/feature_extractor/test_band_ratio_feature_extractor.py
laserchicken/feature_extractor/test_density_absolute_mean_z_extractor.py
laserchicken/feature_extractor/test_density_extractor.py
laserchicken-0.7.0.dist-info/LICENSE
laserchicken-0.7.0.dist-info/METADATA
laserchicken-0.7.0.dist-info/WHEEL
laserchicken-0.7.0.dist-info/entry_points.txt
laserchicken-0.7.0.dist-info/top_level.txt
laserchicken-0.7.0.dist-info/RECORD
