Metadata-Version: 2.1
Name: laserchicken
Version: 0.7.0
Summary: Point cloud toolkit
Home-page: https://github.com/eEcoLiDAR/eEcoLiDAR
License: Apache 2.0
Keywords: Python,Point cloud
Classifier: License :: OSI Approved :: Apache Software License
Classifier: Programming Language :: Python
License-File: LICENSE
Requires-Dist: laspy[lazrs]
Requires-Dist: scipy>=0.11
Requires-Dist: pytest
Requires-Dist: mock
Requires-Dist: plyfile
Requires-Dist: python-dateutil
Requires-Dist: shapely>=2
Requires-Dist: PyShp
Requires-Dist: pandas
Requires-Dist: click
Requires-Dist: colorama
Requires-Dist: psutil
Requires-Dist: numpy
